{
  "type": "Feature",
  "geometry": {
    "type": "Point",
    "coordinates": [
      137.41003561091117,
      34.701695575575755
    ]
  },
  "properties": {
    "name": "B1学生実験棟",
    "label:ja": "B1学生実験棟",
    "label:en": "B1 Building",
    "icon": "b_building"
  }
}