{
  "type": "Feature",
  "geometry": {
    "type": "Point",
    "coordinates": [
      137.40828480996248,
      34.70248814569504
    ]
  },
  "properties": {
    "name": "E2低層実験棟",
    "label:ja": "E2低層実験棟",
    "label:en": "",
    "icon": "e_building"
  }
}