{
  "type": "Feature",
  "geometry": {
    "type": "Point",
    "coordinates": [
      137.41275944830795,
      34.70087834660231
    ]
  },
  "properties": {
    "name": "バス停",
    "label:ja": "バス停",
    "label:en": "Bus Stop",
    "icon": "bus_stop"
  }
}