{
  "type": "Feature",
  "geometry": {
    "type": "Point",
    "coordinates": [
      137.40595618029727,
      34.70103825765955
    ]
  },
  "properties": {
    "name": "体育館",
    "label:ja": "体育館",
    "label:en": "",
    "icon": "gym"
  }
}