{
  "type": "Feature",
  "geometry": {
    "type": "Point",
    "coordinates": [
      137.4053941065145,
      34.70296218547591
    ]
  },
  "properties": {
    "name": "学生宿舎A棟",
    "label:ja": "学生宿舎A棟",
    "label:en": "",
    "icon": "dormitory"
  }
}