{
  "type": "Feature",
  "geometry": {
    "type": "Point",
    "coordinates": [
      137.40436684974998,
      34.70286294344531
    ]
  },
  "properties": {
    "name": "学生宿舎C棟",
    "label:ja": "学生宿舎C棟",
    "label:en": "",
    "icon": "dormitory"
  }
}