{
  "type": "Feature",
  "geometry": {
    "type": "Point",
    "coordinates": [
      137.41308816734335,
      34.70055767468848
    ]
  },
  "properties": {
    "name": "守衛所",
    "label:ja": "守衛所",
    "label:en": "Guard House"
  }
}