{
  "type": "Feature",
  "geometry": {
    "type": "Point",
    "coordinates": [
      137.406929408027,
      34.70004451606209
    ]
  },
  "properties": {
    "name": "生活廃水処理施設",
    "label:ja": "生活廃水処理施設",
    "label:en": ""
  }
}