{
  "type": "Feature",
  "geometry": {
    "type": "Point",
    "coordinates": [
      137.40851137062032,
      34.70315417933436
    ]
  },
  "properties": {
    "name": "自然エネルギー実験棟",
    "label:ja": "自然エネルギー実験棟",
    "label:en": ""
  }
}