{
  "type": "Feature",
  "geometry": {
    "type": "Point",
    "coordinates": [
      137.40900851058967,
      34.70156532974836
    ]
  },
  "properties": {
    "id": 10,
    "name": "C2研究実験棟",
    "group": "C棟群",
    "children": []
  }
}